scalefc/__init__.py
scalefc/__main__.py
scalefc/scalefc.py
scalefc/util.py
scalefc-0.1.1.dist-info/licenses/LICENSE
scalefc-0.1.1.dist-info/METADATA
scalefc-0.1.1.dist-info/WHEEL
scalefc-0.1.1.dist-info/entry_points.txt
scalefc-0.1.1.dist-info/top_level.txt
scalefc-0.1.1.dist-info/RECORD
