Metadata-Version: 2.4
Name: scalefc
Version: 0.1.1
Summary: The official implementation of ScaleFC algorithm for geographical flow (OD flow) data.
Author-email: chenhuan <chen_huan@whu.edu.cn>
License-Expression: MIT
Project-URL: Homepage, https://github.com/ZPGuiGroupWhu/scalefc-pkg
Project-URL: Repository, https://github.com/ZPGuiGroupWhu/scalefc-pkg.git
Project-URL: Issues, https://github.com/ZPGuiGroupWhu/scalefc-pkg/issues
Keywords: flow clustering,geographical flow,density-based flow clustering,origin-destination flow
Classifier: Development Status :: 3 - Alpha
Classifier: Intended Audience :: Science/Research
Classifier: Programming Language :: Python :: 3
Classifier: Programming Language :: Python :: 3.10
Classifier: Programming Language :: Python :: 3.11
Classifier: Programming Language :: Python :: 3.12
Requires-Python: >=3.10
License-File: LICENSE
Requires-Dist: click>=8.2.1
Requires-Dist: pandas>=2.3.0
Requires-Dist: requests>=2.32.5
Requires-Dist: scikit-learn>=1.7.0
Dynamic: license-file
